AUTHORS.rst
HISTORY.rst
LICENSE
MANIFEST.in
README.rst
setup.cfg
setup.py
docs/Makefile
docs/authors.rst
docs/conf.py
docs/contributing.rst
docs/history.rst
docs/index.rst
docs/installation.rst
docs/make.bat
docs/readme.rst
docs/usage.rst
rabird/__init__.py
rabird.selenium.egg-info/PKG-INFO
rabird.selenium.egg-info/SOURCES.txt
rabird.selenium.egg-info/dependency_links.txt
rabird.selenium.egg-info/entry_points.txt
rabird.selenium.egg-info/not-zip-safe
rabird.selenium.egg-info/requires.txt
rabird.selenium.egg-info/top_level.txt
rabird/selenium/__init__.py
rabird/selenium/__main__.py
rabird/selenium/daemon.py
rabird/selenium/exceptions.py
rabird/selenium/expected_conditions.py
rabird/selenium/selenium.py
rabird/selenium/ui.py
rabird/selenium/utils.py
rabird/selenium/validators.py
rabird/selenium/executor/__init__.py
rabird/selenium/executor/chrome.py
rabird/selenium/executor/common.py
rabird/selenium/executor/firefox.py
rabird/selenium/overrides/__init__.py
rabird/selenium/overrides/switch_to.py
rabird/selenium/overrides/webdriver.py
rabird/selenium/overrides/webelement.py
rabird/selenium/webdriver/__init__.py
rabird/selenium/webdriver/dockerized/__init__.py
rabird/selenium/webdriver/dockerized/options.py
rabird/selenium/webdriver/dockerized/webdriver.py
tests/__init__.py
tests/test_rabird_selenium.py